gromp/__init__.py
gromp/__version__.py
gromp/api/__init__.py
gromp/api/accounts/Accountv1Api.py
gromp/api/accounts/__init__.py
gromp/api/base.py
gromp/api/league/ChampionMasteryv4Api.py
gromp/api/league/Championv3Api.py
gromp/api/league/Clashv1Api.py
gromp/api/league/LeagueExpv4Api.py
gromp/api/league/Leaguev4Api.py
gromp/api/league/LolChallengesv1Api.py
gromp/api/league/LolStatusv4Api.py
gromp/api/league/Matchv5Api.py
gromp/api/league/Spectatorv4Api.py
gromp/api/league/Summonerv4Api.py
gromp/api/league/TournamentStubv5Api.py
gromp/api/league/Tournamentv5Api.py
gromp/api/league/__init__.py
gromp/api/lor/LorDeckv1Api.py
gromp/api/lor/LorInventoryv1Api.py
gromp/api/lor/LorMatchv1Api.py
gromp/api/lor/LorRankedv1Api.py
gromp/api/lor/LorStatusv1Api.py
gromp/api/lor/__init__.py
gromp/api/tft/TftLeaguev1Api.py
gromp/api/tft/TftMatchv1Api.py
gromp/api/tft/TftStatusv1Api.py
gromp/api/tft/TftSummonerv1Api.py
gromp/api/tft/__init__.py
gromp/api/valorant/ValContentv1Api.py
gromp/api/valorant/ValMatchv1Api.py
gromp/api/valorant/ValRankedv1Api.py
gromp/api/valorant/ValStatusv1Api.py
gromp/api/valorant/__init__.py
gromp/endpoint/__init__.py
gromp/endpoint/accounts/Accountv1.py
gromp/endpoint/accounts/__init__.py
gromp/endpoint/base.py
gromp/endpoint/league/ChampionMasteryv4.py
gromp/endpoint/league/Championv3.py
gromp/endpoint/league/Clashv1.py
gromp/endpoint/league/LeagueExpv4.py
gromp/endpoint/league/Leaguev4.py
gromp/endpoint/league/LolChallengesv1.py
gromp/endpoint/league/LolStatusv4.py
gromp/endpoint/league/Matchv5.py
gromp/endpoint/league/Spectatorv4.py
gromp/endpoint/league/Summonerv4.py
gromp/endpoint/league/TournamentStubv5.py
gromp/endpoint/league/Tournamentv5.py
gromp/endpoint/league/__init__.py
gromp/endpoint/lor/LorDeckv1.py
gromp/endpoint/lor/LorInventoryv1.py
gromp/endpoint/lor/LorMatchv1.py
gromp/endpoint/lor/LorRankedv1.py
gromp/endpoint/lor/LorStatusv1.py
gromp/endpoint/lor/__init__.py
gromp/endpoint/tft/TftLeaguev1.py
gromp/endpoint/tft/TftMatchv1.py
gromp-1.1.0.dist-info/LICENSE
gromp-1.1.0.dist-info/METADATA
gromp-1.1.0.dist-info/WHEEL
gromp-1.1.0.dist-info/RECORD
