Metadata-Version: 2.1
Name: gromp
Version: 1.1.0
Summary: Holistic Python implementation of the public Riot Games Developer API.
Home-page: https://github.com/wilhelmagren/gromp
License: MIT
Keywords: python,api,league-of-legends,discord-bot,api-wrapper,riot-games,riot,riot-games-api,teamfight-tactics,legends-of-runeterra,valorant
Author: Wilhelm Ågren
Author-email: wilhelmagren98@gmail.com
Requires-Python: >=3.8,<3.13
Classifier: Intended Audience :: Developers
Classifier: License :: OSI Approved :: MIT License
Classifier: Operating System :: OS Independent
Classifier: Programming Language :: Python :: 3
Classifier: Programming Language :: Python :: 3.8
Classifier: Programming Language :: Python :: 3.9
Classifier: Programming Language :: Python :: 3.10
Classifier: Programming Language :: Python :: 3.11
Classifier: Programming Language :: Python :: 3.12
Requires-Dist: requests (>=2.31.0,<3.0.0)
Requires-Dist: rsa (>=4.9,<5.0)
Project-URL: Bug tracker, https://github.com/wilhelmagren/gromp/issues
Project-URL: Repository, https://github.com/wilhelmagren/gromp
